avocado_messenger_server/__init__.py
avocado_messenger_server/bd_server_app.py
avocado_messenger_server/log_config.py
avocado_messenger_server/server.py
avocado_messenger_server-0.0.2.dist-info/DESCRIPTION.rst
avocado_messenger_server-0.0.2.dist-info/METADATA
avocado_messenger_server-0.0.2.dist-info/RECORD
avocado_messenger_server-0.0.2.dist-info/WHEEL
avocado_messenger_server-0.0.2.dist-info/entry_points.txt
avocado_messenger_server-0.0.2.dist-info/metadata.json
avocado_messenger_server-0.0.2.dist-info/top_level.txt
