Metadata-Version: 2.0
Name: avocado-messenger-server
Version: 0.0.2
Summary: Server for avocado_messenger
Home-page: https://github.com/chud0/avocado_messenger_server
Author: chud0
Author-email: www.chud0@mail.ru
License: UNKNOWN
Platform: UNKNOWN
Classifier: Development Status :: 3 - Alpha
Classifier: Programming Language :: Python :: 3.6
Requires-Python: >=3
Requires-Dist: SQLAlchemy
Requires-Dist: avocado-messenger-protocol
